flake8_pydantic_fields
