Metadata-Version: 2.1
Name: flake8-pydantic-fields
Version: 0.1.11
Requires-Python: >=3.10
License-File: LICENSE
